bb.py
setup.py
Bookbank.egg-info/PKG-INFO
Bookbank.egg-info/SOURCES.txt
Bookbank.egg-info/dependency_links.txt
Bookbank.egg-info/requires.txt
Bookbank.egg-info/top_level.txt
bookbank/__init__.py
bookbank/app.py
bookbank/cli.py
bookbank/controllers.py
bookbank/core.py
bookbank/daemon.py
bookbank/database.py
bookbank/forms.py
bookbank/logging.py
bookbank/models.py
bookbank/serializers.py
bookbank/server.py
bookbank/settings.py
bookbank/views.py
bookbank/commands/__init__.py
bookbank/commands/daemon.py
bookbank/commands/search.py
bookbank/dbtypes/__init__.py
bookbank/dbtypes/uuid.py
bookbank/interfaces/__init__.py
bookbank/util/__init__.py
bookbank/util/cl.py