Metadata-Version: 1.1
Name: Bookbank
Version: 0.0.1
Summary: Book manager and automatic downloader
Home-page: https://www.github.com/bookbank/bookbank
Author: nikcub
Author-email: nikcub@gmail.com
License: MIT
Keywords: ebook,book
Platform: UNKNOWN
Classifier: Development Status :: 3 - Alpha
